dinari_api_sdk/__init__.py
dinari_api_sdk/_base_client.py
dinari_api_sdk/_client.py
dinari_api_sdk/_compat.py
dinari_api_sdk/_constants.py
dinari_api_sdk/_exceptions.py
dinari_api_sdk/_files.py
dinari_api_sdk/_models.py
dinari_api_sdk/_qs.py
dinari_api_sdk/_resource.py
dinari_api_sdk/_response.py
dinari_api_sdk/_streaming.py
dinari_api_sdk/_types.py
dinari_api_sdk/_version.py
dinari_api_sdk/py.typed
dinari_api_sdk/_utils/__init__.py
dinari_api_sdk/_utils/_compat.py
dinari_api_sdk/_utils/_datetime_parse.py
dinari_api_sdk/_utils/_logs.py
dinari_api_sdk/_utils/_proxy.py
dinari_api_sdk/_utils/_reflection.py
dinari_api_sdk/_utils/_resources_proxy.py
dinari_api_sdk/_utils/_streams.py
dinari_api_sdk/_utils/_sync.py
dinari_api_sdk/_utils/_transform.py
dinari_api_sdk/_utils/_typing.py
dinari_api_sdk/_utils/_utils.py
dinari_api_sdk/lib/.keep
dinari_api_sdk/resources/__init__.py
dinari_api_sdk/resources/v2/__init__.py
dinari_api_sdk/resources/v2/v2.py
dinari_api_sdk/resources/v2/accounts/__init__.py
dinari_api_sdk/resources/v2/accounts/accounts.py
dinari_api_sdk/resources/v2/accounts/activities.py
dinari_api_sdk/resources/v2/accounts/order_fulfillments.py
dinari_api_sdk/resources/v2/accounts/orders.py
dinari_api_sdk/resources/v2/accounts/token_transfers.py
dinari_api_sdk/resources/v2/accounts/withdrawal_requests.py
dinari_api_sdk/resources/v2/accounts/withdrawals.py
dinari_api_sdk/resources/v2/accounts/order_requests/__init__.py
dinari_api_sdk/resources/v2/accounts/order_requests/eip155.py
dinari_api_sdk/resources/v2/accounts/order_requests/order_requests.py
dinari_api_sdk/resources/v2/accounts/wallet/__init__.py
dinari_api_sdk/resources/v2/accounts/wallet/external.py
dinari_api_sdk/resources/v2/accounts/wallet/wallet.py
dinari_api_sdk/resources/v2/entities/__init__.py
dinari_api_sdk/resources/v2/entities/accounts.py
dinari_api_sdk/resources/v2/entities/entities.py
dinari_api_sdk/resources/v2/entities/kyc/__init__.py
dinari_api_sdk/resources/v2/entities/kyc/document.py
dinari_api_sdk-0.11.0.dist-info/METADATA
dinari_api_sdk-0.11.0.dist-info/WHEEL
dinari_api_sdk-0.11.0.dist-info/licenses/LICENSE
dinari_api_sdk-0.11.0.dist-info/RECORD
